{
  "project_info": {
    "project_number": "836551128976",
    "firebase_url": "https://thetimeline-b232a-default-rtdb.firebaseio.com",
    "project_id": "thetimeline-b232a",
    "storage_bucket": "thetimeline-b232a.appspot.com"
  },
  "client": [
    {
      "client_info": {
        "mobilesdk_app_id": "1:836551128976:android:ffe89e982f89995d9f2515",
        "android_client_info": {
          "package_name": "com.asafk.thetimeline"
        }
      },
      "oauth_client": [
        {
          "client_id": "836551128976-kg91n0q8o479p918c58i78289cupuija.apps.googleusercontent.com",
          "client_type": 1,
          "android_info": {
            "package_name": "com.asafk.thetimeline",
            "certificate_hash": "41b15b49c19cf348f10cd1538a58eccb3e2ce4b9"
          }
        },
        {
          "client_id": "836551128976-jaa5k8e0oq7rdbs8ph8bdp02e25ee4tu.apps.googleusercontent.com",
          "client_type": 3
        }
      ],
      "api_key": [
        {
          "current_key": "AIzaSyDuIWf4ThdHCw-vu27UOqiSNEqtpQ9yn2I"
        }
      ],
      "services": {
        "appinvite_service": {
          "other_platform_oauth_client": [
            {
              "client_id": "836551128976-jaa5k8e0oq7rdbs8ph8bdp02e25ee4tu.apps.googleusercontent.com",
              "client_type": 3
            }
          ]
        }
      }
    }
  ],
  "configuration_version": "1"
}